arxivql/__init__.py
arxivql/_query.py
arxivql/taxonomy.py
arxivql-0.2.2.dist-info/LICENSE
arxivql-0.2.2.dist-info/METADATA
arxivql-0.2.2.dist-info/WHEEL
arxivql-0.2.2.dist-info/RECORD
