Metadata-Version: 2.1
Name: arxivql
Version: 0.2.2
Summary: A pythonic query builder for arXiv search API
Home-page: https://github.com/romazu/arxivql
License: MIT
Keywords: arxiv,api,academic,articles,query,language,dsl
Author: Roman Zubov
Author-email: romazu@protonmail.com
Requires-Python: >=3.7,<4.0
Classifier: Development Status :: 4 - Beta
Classifier: Intended Audience :: Science/Research
Classifier: License :: OSI Approved :: MIT License
Classifier: Programming Language :: Python :: 3
Classifier: Programming Language :: Python :: 3.7
Classifier: Programming Language :: Python :: 3.8
Classifier: Programming Language :: Python :: 3.9
Classifier: Programming Language :: Python :: 3.10
Classifier: Programming Language :: Python :: 3.11
Classifier: Programming Language :: Python :: 3.12
Classifier: Topic :: Scientific/Engineering
Project-URL: Repository, https://github.com/romazu/arxivql
